pychesscom/__init__.py
pychesscom/clients/__init__.py
pychesscom/clients/base_client.py
pychesscom/clients/main_client.py
pychesscom/endpoints/__init__.py
pychesscom/endpoints/club.py
pychesscom/endpoints/country.py
pychesscom/endpoints/leaderboard.py
pychesscom/endpoints/match.py
pychesscom/endpoints/player.py
pychesscom/endpoints/puzzle.py
pychesscom/endpoints/streamer.py
pychesscom/endpoints/tournament.py
pychesscom/utils/__init__.py
pychesscom/utils/response.py
pychesscom/utils/route.py
pychesscom-0.1.3.dist-info/LICENSE
pychesscom-0.1.3.dist-info/METADATA
pychesscom-0.1.3.dist-info/WHEEL
pychesscom-0.1.3.dist-info/top_level.txt
pychesscom-0.1.3.dist-info/RECORD
