Metadata-Version: 2.1
Name: pychesscom
Version: 0.1.3
Summary: An asynchronous Python client for Chess.com's API
Home-page: https://github.com/vopani/pychesscom
Author: Rohan Rao
Author-email: rohanrao88@gmail.com
License: Apache License, Version 2.0
Project-URL: Documentation, https://pychesscom.readthedocs.io/
Project-URL: Source, https://github.com/vopani/pychesscom
Project-URL: Tracker, https://github.com/vopani/pychesscom/issues
Keywords: api,async,chess,client
Platform: any
Classifier: Programming Language :: Python :: 3.7
Classifier: Programming Language :: Python :: 3.8
Classifier: Programming Language :: Python :: 3.9
Classifier: License :: OSI Approved :: Apache Software License
Classifier: Operating System :: OS Independent
Requires-Python: >=3.7
Requires-Dist: aiohttp
